{
  "active_db_path": "/Users/rayfung/Documents/VCC/LeoPaper/LeoPaperSmartManufacturingPlatform/manufacturing_data.db",
  "activation_validation_db_path": "/Users/rayfung/.codex/memories/task14f_working_mirror_20260419.db",
  "activation_validation_db_sha1": "40a3300e3915fd7e9928e8ef18c2f0a423e08943",
  "activation_validation_db_month_range": [
    "2025-01",
    "2026-02"
  ],
  "activation_validation_notes": "Task14F promotion and post-activation smokes were validated against the verified working DB mirror because the repo-local DB path was not re-proven healthy in-session.",
  "all_model_metrics": {
    "linear_regression": {
      "distinct_machines_retained": 84,
      "eval_months": [
        "January 2026",
        "February 2026"
      ],
      "eval_rows": 50675,
      "evaluation_strategy": "time_aware_multi_month_holdout",
      "mae": 0.046101496332793354,
      "r2_score": 0.006707922657925303,
      "rmse": 0.31032360909301165,
      "rows_after_filtering": 364399,
      "rows_after_hard_block": 367737,
      "rows_loaded": 879978,
      "train_months": [
        "January 2025",
        "February 2025",
        "March 2025",
        "April 2025",
        "May 2025",
        "June 2025",
        "July 2025",
        "August 2025",
        "September 2025",
        "October 2025",
        "November 2025",
        "December 2025"
      ],
      "train_rows": 313724
    },
    "random_forest": {
      "distinct_machines_retained": 84,
      "eval_months": [
        "January 2026",
        "February 2026"
      ],
      "eval_rows": 50675,
      "evaluation_strategy": "time_aware_multi_month_holdout",
      "mae": 0.012804444950338988,
      "r2_score": 0.812714004142606,
      "rmse": 0.13475006522302904,
      "rows_after_filtering": 364399,
      "rows_after_hard_block": 367737,
      "rows_loaded": 879978,
      "train_months": [
        "January 2025",
        "February 2025",
        "March 2025",
        "April 2025",
        "May 2025",
        "June 2025",
        "July 2025",
        "August 2025",
        "September 2025",
        "October 2025",
        "November 2025",
        "December 2025"
      ],
      "train_rows": 313724
    },
    "xgboost": {
      "distinct_machines_retained": 84,
      "eval_months": [
        "January 2026",
        "February 2026"
      ],
      "eval_rows": 50675,
      "evaluation_strategy": "time_aware_multi_month_holdout",
      "mae": 0.018341191294290352,
      "r2_score": 0.45202642295959194,
      "rmse": 0.23049215083984392,
      "rows_after_filtering": 364399,
      "rows_after_hard_block": 367737,
      "rows_loaded": 879978,
      "train_months": [
        "January 2025",
        "February 2025",
        "March 2025",
        "April 2025",
        "May 2025",
        "June 2025",
        "July 2025",
        "August 2025",
        "September 2025",
        "October 2025",
        "November 2025",
        "December 2025"
      ],
      "train_rows": 313724
    }
  },
  "artifact_path": "/Users/rayfung/Documents/VCC/LeoPaper/LeoPaperSmartManufacturingPlatform/models/production_preprocessor.pkl",
  "artifact_role": "preprocessor",
  "artifact_state": "active",
  "artifact_version_id": "20260419_181842",
  "backup_model_path": "/Users/rayfung/Documents/VCC/LeoPaper/LeoPaperSmartManufacturingPlatform/models/task14f_artifacts/live_backup_20260419_181842/production_efficiency_model.pkl",
  "backup_preprocessor_path": "/Users/rayfung/Documents/VCC/LeoPaper/LeoPaperSmartManufacturingPlatform/models/task14f_artifacts/live_backup_20260419_181842/production_preprocessor.pkl",
  "candidate_model_path": "/Users/rayfung/Documents/VCC/LeoPaper/LeoPaperSmartManufacturingPlatform/models/task14c_artifacts/staged_candidate_20260418_070130/production_efficiency_model.candidate.task14c.pkl",
  "candidate_preprocessor_path": "/Users/rayfung/Documents/VCC/LeoPaper/LeoPaperSmartManufacturingPlatform/models/task14c_artifacts/staged_candidate_20260418_070130/production_preprocessor.candidate.task14c.pkl",
  "distinct_machines_after_filtering": 84,
  "eval_months": [
    "January 2026",
    "February 2026"
  ],
  "eval_rows": 50675,
  "evaluation_strategy": "time_aware_multi_month_holdout",
  "feature_columns": [
    "hour_of_day",
    "day_of_week",
    "month",
    "is_weekend",
    "is_night_shift",
    "machine_type_encoded",
    "machine_number",
    "team_size",
    "task_complexity",
    "hours_since_last_maintenance",
    "maintenance_urgency",
    "needs_maintenance",
    "maintenance_intensity_30d",
    "cumulative_maintenance_count",
    "production_qty",
    "last_maintenance_type_encoded",
    "team_leader_encoded",
    "material_code_encoded"
  ],
  "feature_contract_version": "canonical_fact_machine_hour_ml_v1",
  "model_path": "/Users/rayfung/Documents/VCC/LeoPaper/LeoPaperSmartManufacturingPlatform/models/production_efficiency_model.pkl",
  "month_coverage": [
    "January 2025",
    "February 2025",
    "March 2025",
    "April 2025",
    "May 2025",
    "June 2025",
    "July 2025",
    "August 2025",
    "September 2025",
    "October 2025",
    "November 2025",
    "December 2025",
    "January 2026",
    "February 2026"
  ],
  "predictor_smoke": {
    "passed": true,
    "prediction_source": "model",
    "predicted_efficiency": 0.016713657957883175,
    "confidence": 0.7081282609418037,
    "sample_machine_id": "024-058",
    "sample_hour_ts": "2026-02-01T00:00:00",
    "sample_month": "February 2026",
    "support_path": "",
    "mirror_db_path": "/Users/rayfung/.codex/memories/task14f_working_mirror_20260419.db"
  },
  "post_activation_smokes": {
    "ml_smoke_passed": true,
    "optimization_smoke_passed": true,
    "experimental_scheduling_smoke_passed": true,
    "smoke_month": "February 2026",
    "smoke_db_path": "/Users/rayfung/.codex/memories/task14f_working_mirror_20260419.db"
  },
  "preprocessor_path": "/Users/rayfung/Documents/VCC/LeoPaper/LeoPaperSmartManufacturingPlatform/models/production_preprocessor.pkl",
  "promoted_at": "2026-04-19T18:18:42+08:00",
  "promotion_success": true,
  "rows_after_filtering": 364399,
  "rows_after_hard_block": 367737,
  "rows_loaded": 879978,
  "selected_model": "random_forest",
  "selected_model_metrics": {
    "distinct_machines_retained": 84,
    "eval_months": [
      "January 2026",
      "February 2026"
    ],
    "eval_rows": 50675,
    "evaluation_strategy": "time_aware_multi_month_holdout",
    "mae": 0.012804444950338988,
    "r2_score": 0.812714004142606,
    "rmse": 0.13475006522302904,
    "rows_after_filtering": 364399,
    "rows_after_hard_block": 367737,
    "rows_loaded": 879978,
    "train_months": [
      "January 2025",
      "February 2025",
      "March 2025",
      "April 2025",
      "May 2025",
      "June 2025",
      "July 2025",
      "August 2025",
      "September 2025",
      "October 2025",
      "November 2025",
      "December 2025"
    ],
    "train_rows": 313724
  },
  "task_tag": "Task 14F",
  "train_months": [
    "January 2025",
    "February 2025",
    "March 2025",
    "April 2025",
    "May 2025",
    "June 2025",
    "July 2025",
    "August 2025",
    "September 2025",
    "October 2025",
    "November 2025",
    "December 2025"
  ],
  "train_rows": 313724,
  "trained_at": "2026-04-18T04:44:55.687175",
  "training_source": "fact_machine_hour"
}
